gitzebo
