Metadata-Version: 1.0
Name: gitzebo
Version: 0.0.10
Summary: A minimal git management web application.
Home-page: http://jgilik.com/gitzebo/
Author: John Gilik
Author-email: john@jgilik.com
License: 2-Clause BSD License
Keywords: git
Platform: UNKNOWN
Classifier: Development Status :: 3 - Alpha
